tomlcv/__init__.py
tomlcv/cv.j2
tomlcv-0.0.5.dist-info/METADATA
tomlcv-0.0.5.dist-info/WHEEL
tomlcv-0.0.5.dist-info/entry_points.txt
tomlcv-0.0.5.dist-info/RECORD
