Metadata-Version: 2.1
Name: tomlcv
Version: 0.0.5
Summary: 
Author: Gilad Kutiel
Author-email: gilad.kutiel@gmail.com
Requires-Python: >=3.13,<4.0
Classifier: Programming Language :: Python :: 3
Requires-Dist: cattrs (>=24.1.2,<25.0.0)
Requires-Dist: jinja2 (>=3.1.4,<4.0.0)
Requires-Dist: toml (>=0.10.2,<0.11.0)
Requires-Dist: typer (>=0.15.1,<0.16.0)
